{"assets/icons/a-filled.png":["assets/icons/a-filled.png"],"assets/icons/b-filled.png":["assets/icons/b-filled.png"],"assets/icons/dpad-down.png":["assets/icons/dpad-down.png"],"assets/icons/dpad-left.png":["assets/icons/dpad-left.png"],"assets/icons/dpad-right.png":["assets/icons/dpad-right.png"],"assets/icons/dpad-up.png":["assets/icons/dpad-up.png"],"assets/icons/dpad.png":["assets/icons/dpad.png"],"assets/icons/left-bumper.png":["assets/icons/left-bumper.png"],"assets/icons/left-joystick-all.png":["assets/icons/left-joystick-all.png"],"assets/icons/left-joystick-down.png":["assets/icons/left-joystick-down.png"],"assets/icons/left-joystick-left.png":["assets/icons/left-joystick-left.png"],"assets/icons/left-joystick-press.png":["assets/icons/left-joystick-press.png"],"assets/icons/left-joystick-right.png":["assets/icons/left-joystick-right.png"],"assets/icons/left-joystick-up.png":["assets/icons/left-joystick-up.png"],"assets/icons/left-joystick.png":["assets/icons/left-joystick.png"],"assets/icons/left-stick.png":["assets/icons/left-stick.png"],"assets/icons/left-trigger.png":["assets/icons/left-trigger.png"],"assets/icons/menu.png":["assets/icons/menu.png"],"assets/icons/right-bumper.png":["assets/icons/right-bumper.png"],"assets/icons/right-joystick-all.png":["assets/icons/right-joystick-all.png"],"assets/icons/right-joystick-down.png":["assets/icons/right-joystick-down.png"],"assets/icons/right-joystick-left.png":["assets/icons/right-joystick-left.png"],"assets/icons/right-joystick-press.png":["assets/icons/right-joystick-press.png"],"assets/icons/right-joystick-right.png":["assets/icons/right-joystick-right.png"],"assets/icons/right-joystick-up.png":["assets/icons/right-joystick-up.png"],"assets/icons/right-joystick.png":["assets/icons/right-joystick.png"],"assets/icons/right-stick.png":["assets/icons/right-stick.png"],"assets/icons/right-trigger.png":["assets/icons/right-trigger.png"],"assets/icons/view.png":["assets/icons/view.png"],"assets/icons/x-filled.png":["assets/icons/x-filled.png"],"assets/icons/y-filled.png":["assets/icons/y-filled.png"],"assets/signin.png":["assets/signin.png"]}